rpis_lib/CTG.py
rpis_lib/__init__.py
rpis_lib/consts.py
rpis_lib/data.py
rpis_lib/estimator.py
rpis_lib/generator.py
rpis_lib/hypothesis.py
rpis_lib/classes/__init__.py
rpis_lib/classes/alfa_wrapper.py
rpis_lib/classes/enums.py
rpis_lib/classes/lists.py
rpis_lib/classes/parts.py
rpis_lib/classes/range.py
rpis_lib/classes/results.py
rpis_lib/classes/types.py
rpis_lib/classes/typing_fix.py
rpis_lib/classes/utils.py
rpis_lib/classes/warnings.py
rpis_lib-0.0.7.dist-info/METADATA
rpis_lib-0.0.7.dist-info/WHEEL
rpis_lib-0.0.7.dist-info/top_level.txt
rpis_lib-0.0.7.dist-info/RECORD
