Metadata-Version: 2.1
Name: rpis_lib
Version: 0.0.7
Summary: Library for Statistic and Probability written for collage course.
Author: jaanonim
Classifier: Programming Language :: Python :: 3
Classifier: License :: OSI Approved :: MIT License
Classifier: Operating System :: OS Independent
Requires-Python: >=3.10
Requires-Dist: scipy >=1.13.1
